syntheticRNASeq/__init__.py
syntheticRNASeq/syntheticRNASeq.py
syntheticrnaseq-1.0.2.dist-info/licenses/LICENSE.txt
syntheticrnaseq-1.0.2.dist-info/METADATA
syntheticrnaseq-1.0.2.dist-info/WHEEL
syntheticrnaseq-1.0.2.dist-info/top_level.txt
syntheticrnaseq-1.0.2.dist-info/RECORD
