Metadata-Version: 2.4
Name: syntheticRNASeq
Version: 1.0.2
Summary: Generate synthetic RNA-Seq data by sampling a negative binomial distribution.
Author-email: Theodoros Karalis <ttkaralis@gmail.com>
License: MIT
Project-URL: Homepage, https://github.com/ttkaralis/syntheticRNASeq
Project-URL: Issues, https://github.com/ttkaralis/syntheticRNASeq/issues
Classifier: Programming Language :: Python :: 3
Classifier: Programming Language :: Python :: 3.12
Classifier: Operating System :: OS Independent
Requires-Python: >=3.8
License-File: LICENSE.txt
Requires-Dist: numpy>=1.26
Requires-Dist: scipy>=1.11
Requires-Dist: pandas>=2.0
Dynamic: license-file
